config.py
main.py
ise_agent/__init__.py
ise_agent/build_cli.py
ise_agent/cli.py
ise_agent/config_manager.py
ise_agent/download_db.py
modules/__init__.py
modules/document_loader.py
modules/noise.py
modules/pipeline.py
modules/rag_engine.py
modules/vector_manager.py
scripts/__init__.py
scripts/build_kb.py
scripts/finetune_lora.py
scripts/inspect_db.py
scripts/package_db.py
scripts/qwen_qa.py
ise_agent-0.1.1.dist-info/METADATA
ise_agent-0.1.1.dist-info/WHEEL
ise_agent-0.1.1.dist-info/entry_points.txt
ise_agent-0.1.1.dist-info/top_level.txt
ise_agent-0.1.1.dist-info/RECORD
