Metadata-Version: 2.4
Name: ise-agent
Version: 0.1.1
Summary: ISE3309 AI 智能助教系统 - 基于级联式 RAG 架构的课程助教
Author: ISE3309 Team
License: MIT
Classifier: Development Status :: 3 - Alpha
Classifier: Intended Audience :: Education
Classifier: Topic :: Education
Classifier: Programming Language :: Python :: 3
Classifier: Programming Language :: Python :: 3.8
Classifier: Programming Language :: Python :: 3.9
Classifier: Programming Language :: Python :: 3.10
Classifier: Programming Language :: Python :: 3.11
Requires-Python: >=3.8
Requires-Dist: langchain<0.3.0,>=0.2.0
Requires-Dist: langchain-community<0.3.0,>=0.2.0
Requires-Dist: langchain-core<0.3.0,>=0.2.0
Requires-Dist: langchain-huggingface
Requires-Dist: chromadb
Requires-Dist: pypdf
Requires-Dist: nbformat
Requires-Dist: beautifulsoup4
Requires-Dist: requests
Requires-Dist: sentence-transformers
Requires-Dist: tabulate
Requires-Dist: transformers
Requires-Dist: torch
Requires-Dist: peft
Requires-Dist: accelerate
Requires-Dist: datasets
Requires-Dist: google-generativeai
Requires-Dist: openai
Requires-Dist: requests
Requires-Dist: tqdm
